animethemes_webm_verifier-1.3.dist-info/licenses/LICENSE
test_webm/__init__.py
test_webm/__main__.py
test_webm/_test_audio.py
test_webm/_test_format.py
test_webm/_test_group.py
test_webm/_test_video.py
test_webm/_test_webm.py
test_webm/_utils.py
test_webm/_webm_format.py
animethemes_webm_verifier-1.3.dist-info/METADATA
animethemes_webm_verifier-1.3.dist-info/WHEEL
animethemes_webm_verifier-1.3.dist-info/top_level.txt
animethemes_webm_verifier-1.3.dist-info/RECORD
