Metadata-Version: 2.4
Name: animethemes-webm-verifier
Version: 1.3
Summary: Verify WebM(s) Against AnimeThemes Encoding Standards
Home-page: https://github.com/AnimeThemes/animethemes-webm-verifier
Author: AnimeThemes
Author-email: admin@animethemes.moe
Classifier: Intended Audience :: Developers
Classifier: Programming Language :: Python :: 3.14
Classifier: Programming Language :: Python :: 3.15
Classifier: License :: OSI Approved :: MIT License
Classifier: Natural Language :: English
Classifier: Operating System :: OS Independent
Requires-Python: >=3.14
License-File: LICENSE
Requires-Dist: packaging
Dynamic: author
Dynamic: author-email
Dynamic: classifier
Dynamic: description
Dynamic: description-content-type
Dynamic: home-page
Dynamic: license-file
Dynamic: requires-dist
Dynamic: requires-python
Dynamic: summary
